examples/__init__.py
examples/demo_spread_trades_memecoin.py
timeseriesfuser/__init__.py
timeseriesfuser/classes.py
timeseriesfuser/core.py
timeseriesfuser/datasources.py
timeseriesfuser/statics.py
timeseriesfuser/helpers/__init__.py
timeseriesfuser/helpers/helpers.py
timeseriesfuser-0.5.2.dist-info/LICENSE
timeseriesfuser-0.5.2.dist-info/METADATA
timeseriesfuser-0.5.2.dist-info/WHEEL
timeseriesfuser-0.5.2.dist-info/top_level.txt
timeseriesfuser-0.5.2.dist-info/RECORD
