Metadata-Version: 2.1
Name: timeseriesfuser
Version: 0.5.2
Summary: TimeSeriesFuser - Time series data merging with event-driven distribution.
Author-email: Anthony Sweeney <safsweeney@gmail.com>
Project-URL: Homepage, https://github.com/klovanone/timeseriesfuser/
Classifier: Programming Language :: Python :: 3 :: Only
Classifier: Programming Language :: Python :: 3.9
Classifier: Programming Language :: Python :: 3.10
Classifier: Programming Language :: Python :: 3.11
Classifier: License :: OSI Approved :: GNU Affero General Public License v3 or later (AGPLv3+)
Classifier: Intended Audience :: Developers
Classifier: Development Status :: 3 - Alpha
Requires-Python: >=3.9
License-File: LICENSE
Requires-Dist: polars >=0.19.8
Requires-Dist: numpy >=1.22.4
